atdd/__init__.py
atdd/__main__.py
atdd/cli.py
atdd/conftest.py
atdd/version_check.py
atdd/coach/__init__.py
atdd/coach/commands/__init__.py
atdd/coach/commands/add_persistence_metadata.py
atdd/coach/commands/analyze_migrations.py
atdd/coach/commands/consumers.py
atdd/coach/commands/gate.py
atdd/coach/commands/infer_governance_status.py
atdd/coach/commands/initializer.py
atdd/coach/commands/interface.py
atdd/coach/commands/inventory.py
atdd/coach/commands/migration.py
atdd/coach/commands/registry.py
atdd/coach/commands/session.py
atdd/coach/commands/sync.py
atdd/coach/commands/test_interface.py
atdd/coach/commands/test_runner.py
atdd/coach/commands/traceability.py
atdd/coach/commands/tests/__init__.py
atdd/coach/commands/tests/test_telemetry_array_validation.py
atdd/coach/conventions/session.convention.yaml
atdd/coach/overlays/__init__.py
atdd/coach/overlays/claude.md
atdd/coach/schemas/config.schema.json
atdd/coach/schemas/manifest.schema.json
atdd/coach/templates/ATDD.md
atdd/coach/templates/SESSION-TEMPLATE.md
atdd/coach/utils/__init__.py
atdd/coach/utils/repo.py
atdd/coach/utils/graph/__init__.py
atdd/coach/utils/graph/urn.py
atdd/coach/validators/__init__.py
atdd/coach/validators/shared_fixtures.py
atdd/coach/validators/test_enrich_wagon_registry.py
atdd/coach/validators/test_registry.py
atdd/coach/validators/test_release_versioning.py
atdd/coach/validators/test_session_validation.py
atdd/coach/validators/test_traceability.py
atdd/coach/validators/test_update_feature_paths.py
atdd/coach/validators/test_validate_contract_consumers.py
atdd/coder/__init__.py
atdd/coder/conventions/adapter.recipe.yaml
atdd/coder/conventions/backend.convention.yaml
atdd/coder/conventions/boundaries.convention.yaml
atdd/coder/conventions/commons.convention.yaml
atdd/coder/conventions/complexity.recipe.yaml
atdd/coder/conventions/component-naming.convention.yaml
atdd/coder/conventions/design.convention.yaml
atdd/coder/conventions/design.recipe.yaml
atdd-0.4.4.dist-info/licenses/LICENSE
atdd-0.4.4.dist-info/METADATA
atdd-0.4.4.dist-info/WHEEL
atdd-0.4.4.dist-info/entry_points.txt
atdd-0.4.4.dist-info/top_level.txt
atdd-0.4.4.dist-info/RECORD
