Metadata-Version: 2.4
Name: atdd
Version: 0.4.4
Summary: ATDD Platform - Acceptance Test Driven Development toolkit
License: MIT
Requires-Python: >=3.10
License-File: LICENSE
Requires-Dist: pyyaml
Provides-Extra: dev
Requires-Dist: pytest; extra == "dev"
Requires-Dist: pytest-xdist; extra == "dev"
Dynamic: license-file
